{"title": "Corruption by a Minor", "content": "Under US law (and other countries as well), there is a crime known as Corruption of a Minor, in which adults coerce or help children to commit crimes.\n\nThis is the inverse.\n\nSometimes children can convince adults to break the law. But they're such innocent little darlings! How on earth is that possible? They could turn on the charm, particularly on a gullible adult or one with low self-esteem, or one who just likes kids and wants to be nice, or maybe one who sees the kid as an equal or a friend. Other times, the kid simply bribes the adult. This is pretty much the favourite technique of the Enfant Terrible.\n\nSee also Troubling Unchildlike Behavior, Kids Are Cruel, Deliberately Cute Child, From the Mouths of Babes, Corruption of a Minor, and Enfant Terrible.", "url": "https://tvtropes.org/pmwiki/pmwiki.php/Main/CorruptionByAMinor", "media_links": ["/pmwiki/pmwiki.php/Film/LawnDogs", "/pmwiki/pmwiki.php/Manga/Negima", "/pmwiki/pmwiki.php/Anime/Monster", "/pmwiki/pmwiki.php/Manga/KatekyoHitmanReborn", "/pmwiki/pmwiki.php/Film/LittleSweetheart", "/pmwiki/pmwiki.php/Film/LawnDogs", "/pmwiki/pmwiki.php/Film/MatchstickMen", "/pmwiki/pmwiki.php/Creator/Disney", "/pmwiki/pmwiki.php/Film/NoDepositNoReturn", "/pmwiki/pmwiki.php/Literature/Lolita", "/pmwiki/pmwiki.php/Series/MalcolmInTheMiddle", "/pmwiki/pmwiki.php/Series/TheManShow", "/pmwiki/pmwiki.php/Series/ShamelessUS", "/pmwiki/pmwiki.php/Series/CSI", "/pmwiki/pmwiki.php/VisualNovel/PhoenixWrightAceAttorneyTrialsAndTribulations", "/pmwiki/pmwiki.php/Franchise/KingdomHearts", "/pmwiki/pmwiki.php/VideoGame/KingdomHeartsIII", "/pmwiki/pmwiki.php/Webcomic/Concession"], "non_media_links": ["/pmwiki/pmwiki.php/Main/CorruptionOfAMinor", "/pmwiki/pmwiki.php/Main/InvertedTrope", "/pmwiki/pmwiki.php/Main/ChildrenAreInnocent", "/pmwiki/pmwiki.php/Main/EnfantTerrible", "/pmwiki/pmwiki.php/Main/TroublingUnchildlikeBehavior", "/pmwiki/pmwiki.php/Main/KidsAreCruel", "/pmwiki/pmwiki.php/Main/DeliberatelyCuteChild", "/pmwiki/pmwiki.php/Main/FromTheMouthsOfBabes", "/pmwiki/pmwiki.php/Main/CorruptionOfAMinor", "/pmwiki/pmwiki.php/Main/EnfantTerrible", "/pmwiki/pmwiki.php/Main/LoliconAndShotacon", "/pmwiki/pmwiki.php/Main/ChasteHero", "/pmwiki/pmwiki.php/Main/ChickMagnet", "/pmwiki/pmwiki.php/Main/ComedicShotacon", "/pmwiki/pmwiki.php/Main/BigBad", "/pmwiki/pmwiki.php/Main/TheChessmaster", "/pmwiki/pmwiki.php/Main/UnreliableNarrator", "/pmwiki/pmwiki.php/Main/LetsWaitAWhile", "/pmwiki/pmwiki.php/Main/MurderSimulators", "/pmwiki/pmwiki.php/Main/AdultsAreUseless"]}