{"title": "New Eden", "content": "There, in vision, out of the wreck of cities and civilizations,\n\nSlowly out of the ruins of the past,\n\nOut of the litter and muck of a decaying world,\n\nLong before the start of the story, ecological disaster drove humanity undersea, or underground, or into space, away from a ravaged Earth. After living for quite a while in a City in a Bottle, it's a safe bet that someone will eventually find the way out and discover that the Earth has cleaned itself up nicely and now looks like the pristine Ghibli Hills, or why not, the Yosemite National Park.\n\nOften used to make the point that the Earth would be a so much better place if it weren't for all the people, or more succinctly, that Ludd Was Right. If a group of survivors in space is smaller and not planning on a disaster, that's But What About the Astronauts?.\n\nNaturally, this is the perfect setting for an Adam and Eve Plot. May evoke the original Garden of Eden story as well.", "url": "https://tvtropes.org/pmwiki/pmwiki.php/Main/NewEden", "media_links": ["/pmwiki/pmwiki.php/Anime/LastExile", "/pmwiki/pmwiki.php/Anime/EurekaSeven", "/pmwiki/pmwiki.php/Anime/TokyoMewMew", "/pmwiki/pmwiki.php/Manga/NausicaaOfTheValleyOfTheWind", "/pmwiki/pmwiki.php/Anime/PaleCocoon", "/pmwiki/pmwiki.php/Anime/TengenToppaGurrenLagann", "/pmwiki/pmwiki.php/Anime/Megazone23", "/pmwiki/pmwiki.php/Franchise/TheDCU", "/pmwiki/pmwiki.php/ComicBook/TwoThousandAD", "/pmwiki/pmwiki.php/ComicBook/AvengersVsXMen", "/pmwiki/pmwiki.php/ComicBook/WhatIf", "/pmwiki/pmwiki.php/ComicBook/Magneto", "/pmwiki/pmwiki.php/ComicBook/Wolverine", "/pmwiki/pmwiki.php/ComicBook/JeanGrey", "/pmwiki/pmwiki.php/WesternAnimation/WallE", "/pmwiki/pmwiki.php/Creator/Pixar", "/pmwiki/pmwiki.php/Film/LogansRun", "/pmwiki/pmwiki.php/Film/FightClub", "/pmwiki/pmwiki.php/Film/Hellboy2004", "/pmwiki/pmwiki.php/Literature/TheMachineStops", "/pmwiki/pmwiki.php/Creator/EMForster", "/pmwiki/pmwiki.php/Literature/EarthAbides", "/pmwiki/pmwiki.php/Creator/BenElton", "/pmwiki/pmwiki.php/Literature/ThePendragonAdventure", "/pmwiki/pmwiki.php/Creator/AndreNorton", "/pmwiki/pmwiki.php/Literature/NovelsOfTheChange", "/pmwiki/pmwiki.php/Literature/TheStand", "/pmwiki/pmwiki.php/Creator/StephenKing", "/pmwiki/pmwiki.php/Franchise/StarWarsExpandedUniverse", "/pmwiki/pmwiki.php/Creator/AndreyLivadny", "/pmwiki/pmwiki.php/Literature/TheHistoryOfTheGalaxy", "/pmwiki/pmwiki.php/Literature/TheCityOfEmber", "/pmwiki/pmwiki.php/Literature/TheWorldAndThorinn", "/pmwiki/pmwiki.php/Creator/PhilipKDick", "/pmwiki/pmwiki.php/Series/BattlestarGalactica2003", "/pmwiki/pmwiki.php/Series/DoctorWho", "/pmwiki/pmwiki.php/Series/StargateSG1", "/pmwiki/pmwiki.php/Series/Cleopatra2525", "/pmwiki/pmwiki.php/Music/TalkingHeads", "/pmwiki/pmwiki.php/TabletopGame/Mystara", "/pmwiki/pmwiki.php/VideoGame/BreathOfFireDragonQuarter", "/pmwiki/pmwiki.php/VideoGame/CityOfHeroes", "/pmwiki/pmwiki.php/VideoGame/EveOnline", "/pmwiki/pmwiki.php/VideoGame/MegaManX5", "/pmwiki/pmwiki.php/VideoGame/MegaManZero4", "/pmwiki/pmwiki.php/VideoGame/CommandAndConquerTiberiumWars", "/pmwiki/pmwiki.php/VideoGame/ArmoredCore", "/pmwiki/pmwiki.php/VideoGame/MassEffect2", "/pmwiki/pmwiki.php/VideoGame/Civilization", "/pmwiki/pmwiki.php/VideoGame/ArTonelicoIIMelodyOfMetafalica", "/pmwiki/pmwiki.php/VideoGame/ArTonelicoQogaKnellOfArCiel", "/pmwiki/pmwiki.php/VideoGame/EnslavedOdysseyToTheWest", "/pmwiki/pmwiki.php/Franchise/SilentHill", "/pmwiki/pmwiki.php/VideoGame/Fallout3", "/pmwiki/pmwiki.php/WesternAnimation/AdventureTime", "/pmwiki/pmwiki.php/WesternAnimation/JusticeLeague", "/pmwiki/pmwiki.php/WesternAnimation/BeastMachines", "/pmwiki/pmwiki.php/Series/LifeAfterPeople"], "non_media_links": ["/pmwiki/pmwiki.php/Main/EarthThatWas", "/pmwiki/pmwiki.php/Main/CityInABottle", "/pmwiki/pmwiki.php/Main/GhibliHills", "/pmwiki/pmwiki.php/Main/CaliforniaDoubling", "/pmwiki/pmwiki.php/Main/HumansAreBastards", "/pmwiki/pmwiki.php/Main/LuddWasRight", "/pmwiki/pmwiki.php/Main/ButWhatAboutTheAstronauts", "/pmwiki/pmwiki.php/Main/AdamAndEvePlot", "/pmwiki/pmwiki.php/Main/GardenOfEden", "/pmwiki/pmwiki.php/Main/CityInABottle", "/pmwiki/pmwiki.php/Main/EyeCatch", "/pmwiki/pmwiki.php/Main/BigBad", "/pmwiki/pmwiki.php/Main/KillAllHumans", "/pmwiki/pmwiki.php/Main/MacGuffin", "/pmwiki/pmwiki.php/Main/AfterTheEnd", "/pmwiki/pmwiki.php/Main/AbusivePrecursors", "/pmwiki/pmwiki.php/Main/BeyondTheImpossible", "/pmwiki/pmwiki.php/Main/LampshadeHanging", "/pmwiki/pmwiki.php/Main/AIs", "/pmwiki/pmwiki.php/Main/HumanPopsicle", "/pmwiki/pmwiki.php/Main/PhysicalGod", "/pmwiki/pmwiki.php/Main/FinalBattle", "/pmwiki/pmwiki.php/Main/CosmicEntity", "/pmwiki/pmwiki.php/Main/TheEndOfTheWorldAsWeKnowIt", "/pmwiki/pmwiki.php/Main/HealingFactor", "/pmwiki/pmwiki.php/Main/DeusExMachina", "/pmwiki/pmwiki.php/RolePlay/WeAreAllPokemonTrainers", "/pmwiki/pmwiki.php/FanFic/TheConversionBureau", "/pmwiki/pmwiki.php/Main/TheFilmOfTheBook", "/pmwiki/pmwiki.php/Main/EvilSorcerer", "/pmwiki/pmwiki.php/Main/WellIntentionedExtremist", "/pmwiki/pmwiki.php/Main/SealedEvilInACan", "/pmwiki/pmwiki.php/Main/EldritchAbomination", "/pmwiki/pmwiki.php/Main/AxeCrazy", "http://en.wikipedia.org/wiki/Earth_Abides", "/pmwiki/pmwiki.php/Main/FridgeHorror", "/pmwiki/pmwiki.php/Main/CityInABottle", "/pmwiki/pmwiki.php/Main/TheAntichrist", "/pmwiki/pmwiki.php/Main/TheProfessor", "/pmwiki/pmwiki.php/Main/LuddWasRight", "/pmwiki/pmwiki.php/Main/ThePlague", "/pmwiki/pmwiki.php/Main/RobotWar", "/pmwiki/pmwiki.php/Main/LotusEaterMachine", "/pmwiki/pmwiki.php/Main/BigBad", "/pmwiki/pmwiki.php/Main/MonsterClown", "/pmwiki/pmwiki.php/Main/CrapsaccharineWorld", "/pmwiki/pmwiki.php/Main/TheVirus", "/pmwiki/pmwiki.php/Main/MadScientist", "/pmwiki/pmwiki.php/Main/CrapsackWorld", "/pmwiki/pmwiki.php/Main/ColonyDrop", "/pmwiki/pmwiki.php/Main/BigBad", "/pmwiki/pmwiki.php/Main/KillSat", "/pmwiki/pmwiki.php/Main/ToxicPhlebotinum", "/pmwiki/pmwiki.php/Main/Backstory", "/pmwiki/pmwiki.php/Main/AIIsACrapshoot", "/pmwiki/pmwiki.php/Main/DeusEstMachina", "/pmwiki/pmwiki.php/Main/FromBadToWorse", "/pmwiki/pmwiki.php/Main/UtopiaJustifiesTheMeans", "https://www.youtube.com/watch?v=bxBVc2cSFeI", "/pmwiki/pmwiki.php/Main/UtopiaJustifiesTheMeans", "/pmwiki/pmwiki.php/Main/WellIntentionedExtremist", "/pmwiki/pmwiki.php/Main/FromBadToWorse", "/pmwiki/pmwiki.php/Main/FromBadToWorse", "/pmwiki/pmwiki.php/Main/EarnYourHappyEnding", "/pmwiki/pmwiki.php/Main/HopeSproutsEternal", "/pmwiki/pmwiki.php/Main/SubvertedTrope", "/pmwiki/pmwiki.php/Main/InfallibleBabble", "/pmwiki/pmwiki.php/Main/AfterTheEnd", "/pmwiki/pmwiki.php/Main/PsychicPowers", "/pmwiki/pmwiki.php/Main/WorldTree", "/pmwiki/pmwiki.php/Main/HeroicSacrifice", "/pmwiki/pmwiki.php/Main/GeniusLoci", "http://www.sciam.com/article.cfm?chanID=sa006&articleID=2691D716-E7F2-99DF-38F54EF6075AAB4D&pageNumber=1&catID=2", "http://en.wikipedia.org/wiki/European_Green_Belt", "/pmwiki/pmwiki.php/Main/ForbiddenZone", "http://en.wikipedia.org/wiki/Chernobyl_after_the_disaster", "http://www.nsrl.ttu.edu/chornobyl/wildlifepreserve.htm", "/pmwiki/pmwiki.php/Main/ILoveNuclearPower", "http://sg.news.yahoo.com/afp/20100807/tts-germany-hunting-food-chernobyl-509a08e.html"]}