{"title": "Misleading Package Size", "content": "Normally, due to people not wanting to waste too much material, packages tend to be about the same size as what's in them. Not when this trope comes up. In that case, an entire wooden box used for major transport could be used to carry a single pen, a steel suitcase the size of a rifle is used to transport a single ammo clip, etc. Tends to be parodied in cartoons, when they somehow pull a giant 30+ inch TV out of a package the size of a shoebox, in which case it can overlap with Hammer Space.\n\nContrast Bigger on the Inside and Clown Car. Has nothing to do with Bigger Is Better in Bed. Or Gag Penis.", "url": "https://tvtropes.org/pmwiki/pmwiki.php/Main/MisleadingPackageSize", "media_links": ["/pmwiki/pmwiki.php/Franchise/DragonBall", "/pmwiki/pmwiki.php/ComicBook/Iznogoud", "/pmwiki/pmwiki.php/Webcomic/AxisPowersHetalia", "/pmwiki/pmwiki.php/Literature/DiaryOfAWimpyKid", "/pmwiki/pmwiki.php/Series/TheDickVanDykeShow", "/pmwiki/pmwiki.php/Series/ShiningTimeStation", "/pmwiki/pmwiki.php/WesternAnimation/KingOfTheHill", "/pmwiki/pmwiki.php/WesternAnimation/MickeyMouse2013", "/pmwiki/pmwiki.php/WesternAnimation/HowTheGrinchStoleChristmas", "/pmwiki/pmwiki.php/WesternAnimation/ClassicDisneyShorts", "/pmwiki/pmwiki.php/WesternAnimation/DonaldDuck", "/pmwiki/pmwiki.php/WesternAnimation/HowToHookUpYourHomeTheater", "/pmwiki/pmwiki.php/WesternAnimation/Goofy", "/pmwiki/pmwiki.php/WesternAnimation/SpongeBobSquarePants", "/pmwiki/pmwiki.php/WesternAnimation/FamilyGuy", "/pmwiki/pmwiki.php/WesternAnimation/TazMania", "/pmwiki/pmwiki.php/WesternAnimation/BettyBoop", "/pmwiki/pmwiki.php/WesternAnimation/Kaeloo", "/pmwiki/pmwiki.php/WesternAnimation/WildKratts", "/pmwiki/pmwiki.php/Creator/FantasyFlightGames"], "non_media_links": ["/pmwiki/pmwiki.php/Main/HammerSpace", "/pmwiki/pmwiki.php/Main/BiggerOnTheInside", "/pmwiki/pmwiki.php/Main/ClownCar", "/pmwiki/pmwiki.php/Main/BiggerIsBetterInBed", "/pmwiki/pmwiki.php/Main/GagPenis", "/pmwiki/pmwiki.php/Advertising/WheresTheBeef", "/pmwiki/pmwiki.php/Main/MatryoshkaObject", "https://www.fanfiction.net/s/11886910/1/Gankona-Unnachgiebig-Unit%C3%A0", "/pmwiki/pmwiki.php/Main/Parody", "/pmwiki/pmwiki.php/Main/ShowWithinAShow", "/pmwiki/pmwiki.php/Main/InUniverse", "/pmwiki/pmwiki.php/Main/TruthInTelevision", "https://www.youtube.com/watch?v=qGL3zr3xDHU", "/pmwiki/pmwiki.php/Recap/MickeyMouseS1E10GhoulFriend", "/pmwiki/pmwiki.php/Main/SarcasmMode", "/pmwiki/pmwiki.php/Main/ChristmasEpisode", "/pmwiki/pmwiki.php/Main/TruthInTelevision", "/pmwiki/pmwiki.php/Main/TabletopGames"]}