{"title": "Work Hard, Play Hard", "content": "He's the most efficient person in your workplace. He thinks of plans that work better than anybody else's and can take down anyone when he's attacked. He might be a harsh employer or a kind helper who teaches you how to make your work habits more efficient. He is always professional and mature, if not a little too uptight. Either way, you can always rely on him for anything, as long as it's work related.\n\nOne day, he invites you to hang out with him after work. Curious, you agree.\n\nYou're surprised to see him break open the alcohol, start screaming karaoke or show other wild behaviors that you never saw at work. Turns out, he spends as much energy partying as he does working hard. He might even use the fact that he works so hard as an excuse to why he plays so hard.\n\nTruth in Television here, as relaxing and having fun is good way to keep stress levels down. Being social is also a good way to find employment and learn from others, so a complete workaholic is pretty tough to find in Real Life. There's also the fact that most people enjoy having fun and relaxing \u2014 but need to work to earn money. Frequently this is the other side to characters like The Reliable One. You'd think this character would get along well with The Workaholic, who they superficially resemble until The Reveal, and they may get along great during work hours (or be The Rival to each other), but when hanging out this character might find their workaholic colleague to be a buzzkill, that is IF they even agree to hang out.\n\nSub-Trope of More Than Meets the Eye and a subversion of The Workaholic.", "url": "https://tvtropes.org/pmwiki/pmwiki.php/Main/WorkHardPlayHard", "media_links": ["/pmwiki/pmwiki.php/Anime/NeonGenesisEvangelion", "/pmwiki/pmwiki.php/Manga/VirginLove", "/pmwiki/pmwiki.php/Manga/DragonBall", "/pmwiki/pmwiki.php/Series/BuffyTheVampireSlayer", "/pmwiki/pmwiki.php/Film/IronMan", "/pmwiki/pmwiki.php/Film/CharlieWilsonsWar", "/pmwiki/pmwiki.php/Film/StarshipTroopers", "/pmwiki/pmwiki.php/Franchise/StarTrekExpandedUniverse", "/pmwiki/pmwiki.php/Literature/Mash", "/pmwiki/pmwiki.php/Creator/DrSeuss", "/pmwiki/pmwiki.php/Literature/HeraldsOfValdemar", "/pmwiki/pmwiki.php/Literature/TheDresdenFiles", "/pmwiki/pmwiki.php/Literature/TheWheelOfTime", "/pmwiki/pmwiki.php/Series/StarTrekDeepSpaceNine", "/pmwiki/pmwiki.php/Series/Mash", "/pmwiki/pmwiki.php/Series/StargateSG1", "/pmwiki/pmwiki.php/Series/Firefly", "/pmwiki/pmwiki.php/Series/TheBigBangTheory", "/pmwiki/pmwiki.php/Franchise/DragonAge", "/pmwiki/pmwiki.php/VideoGame/TheSecretWorld", "/pmwiki/pmwiki.php/VideoGame/Destiny", "/pmwiki/pmwiki.php/Series/Noob", "/pmwiki/pmwiki.php/WesternAnimation/TheSimpsons", "/pmwiki/pmwiki.php/WesternAnimation/YoungJustice", "/pmwiki/pmwiki.php/Franchise/Batman", "/pmwiki/pmwiki.php/WesternAnimation/MaxSteel", "/pmwiki/pmwiki.php/Franchise/DCAU", "/pmwiki/pmwiki.php/Film/WallStreet", "/pmwiki/pmwiki.php/Film/TheWolfOfWallStreet", "/pmwiki/pmwiki.php/Creator/ChristopherTitus", "/pmwiki/pmwiki.php/Creator/AlbertEinstein"], "non_media_links": ["/pmwiki/pmwiki.php/Main/TheStrategist", "/pmwiki/pmwiki.php/Main/TheLeader", "/pmwiki/pmwiki.php/Main/TheSmartGuy", "/pmwiki/pmwiki.php/Main/BadassBookworm", "/pmwiki/pmwiki.php/Main/MinoredInAsskicking", "/pmwiki/pmwiki.php/Main/DrillSergeantNasty", "/pmwiki/pmwiki.php/Main/BigBrotherMentor", "/pmwiki/pmwiki.php/Main/TruthInTelevision", "/pmwiki/pmwiki.php/Main/RealLife", "/pmwiki/pmwiki.php/Main/TheReliableOne", "/pmwiki/pmwiki.php/Main/TheWorkaholic", "/pmwiki/pmwiki.php/Main/TheReveal", "/pmwiki/pmwiki.php/Main/TheRival", "/pmwiki/pmwiki.php/Main/SubTrope", "/pmwiki/pmwiki.php/Main/MoreThanMeetsTheEye", "/pmwiki/pmwiki.php/Main/SubvertedTrope", "/pmwiki/pmwiki.php/Main/TheWorkaholic", "/pmwiki/pmwiki.php/Main/HardDrinkingPartyGirl", "/pmwiki/pmwiki.php/Main/Salaryman", "/pmwiki/pmwiki.php/Main/OldMaster", "/pmwiki/pmwiki.php/Main/BunnyEarsLawyer", "/pmwiki/pmwiki.php/Main/BoringButPractical", "https://www.tthfanfic.org/story.php?no=30534", "/pmwiki/pmwiki.php/Main/SamaritanSyndrome", "/pmwiki/pmwiki.php/Main/TheFairFolk", "/pmwiki/pmwiki.php/Main/ForeverWar", "/pmwiki/pmwiki.php/Main/EldritchAbomination", "/pmwiki/pmwiki.php/Main/OmnicidalManiac", "/pmwiki/pmwiki.php/Main/NecessaryEvil", "/pmwiki/pmwiki.php/Main/Workaholic", "/pmwiki/pmwiki.php/Main/ElvesVsDwarves", "/pmwiki/pmwiki.php/Main/VetinariJobSecurity", "/pmwiki/pmwiki.php/Main/YouHaveFailedMe", "/pmwiki/pmwiki.php/Main/GodEmperor", "/pmwiki/pmwiki.php/Main/TheEmpire", "/pmwiki/pmwiki.php/Main/StealthHiBye", "/pmwiki/pmwiki.php/Main/CreepyMonotone", "/pmwiki/pmwiki.php/Main/MachoCamp", "https://www.youtube.com/watch?v=WjElZ-O9EpM", "/pmwiki/pmwiki.php/Main/WordOfGod", "/pmwiki/pmwiki.php/Main/RichIdiotWithNoDayJob", "/pmwiki/pmwiki.php/Main/RichIdiotWithNoDayJob", "/pmwiki/pmwiki.php/Main/MillionairePlayboy", "/pmwiki/pmwiki.php/Main/GermanicEfficiency", "/pmwiki/pmwiki.php/Main/OktoberFest", "/pmwiki/pmwiki.php/Main/AsianAndNerdy", "/pmwiki/pmwiki.php/Main/AnimeLand", "/pmwiki/pmwiki.php/Main/AncientRome", "/pmwiki/pmwiki.php/Main/GratuitousLatin", "/pmwiki/pmwiki.php/Main/EveryoneIsBi", "/pmwiki/pmwiki.php/Main/APartyAlsoKnownAsAnOrgy", "/pmwiki/pmwiki.php/Main/GloriousMotherRussia", "/pmwiki/pmwiki.php/Main/VodkaDrunkenski", "/pmwiki/pmwiki.php/Main/MotherRussiaMakesYouStrong", "/pmwiki/pmwiki.php/Main/FromRussiaWithNukes", "https://en.wikipedia.org/wiki/Godiva%27s_Hymn", "/pmwiki/pmwiki.php/Main/TheWomanWearingTheQueenlyMask", "/pmwiki/pmwiki.php/Main/CourtlyLove", "/pmwiki/pmwiki.php/Main/HerrDoktor", "http://www.cracked.com/article_18559_6-famous-geniuses-you-didnt-know-were-perverts.html", "/pmwiki/pmwiki.php/UsefulNotes/LouisXIV", "/pmwiki/pmwiki.php/Main/Workaholic", "https://upserve.com/restaurant-insider/chefs-share-struggles-overcoming-addiction-kitchen/"]}