{"title": "Transfer Student Uniforms", "content": "\"Shorts to school? Man, you kids in Maple Wherever just do whatever the hell you want, don't you?\"\n\nNew Transfer Students in places where school uniforms are a cultural default setting often wear their old ones until the school can provide them with a new one. In fiction, this shows the newcomer or outsider. When they get the current school uniform, this indicates they've been assimilated. If the student is meant to be a Fish out of Water, they will keep their old uniform throughout the series. In Japanese media, even rebels don't choose to abandon uniforms entirely; in American media they will do this even if the new school doesn't have uniforms. Compare the Non-Uniform Uniform.\n\nFor characters Trapped in Another World, having this is not just a case of having a Limited Wardrobe, but to remind the audience that this character is not native. Naturally adopting local clothing is a sign of Going Native. A younger version of Still Wearing the Old Colors.", "url": "https://tvtropes.org/pmwiki/pmwiki.php/Main/TransferStudentUniforms", "media_links": ["/pmwiki/pmwiki.php/Manga/SayonaraZetsubouSensei", "/pmwiki/pmwiki.php/Literature/EthanSuspended", "/pmwiki/pmwiki.php/Manga/OuranHighSchoolHostClub", "/pmwiki/pmwiki.php/Manga/YuYuHakusho", "/pmwiki/pmwiki.php/Anime/RevolutionaryGirlUtena", "/pmwiki/pmwiki.php/Franchise/SailorMoon", "/pmwiki/pmwiki.php/Series/PrettyGuardianSailorMoon", "/pmwiki/pmwiki.php/Anime/JubeiChan", "/pmwiki/pmwiki.php/Manga/MagicKnightRayearth", "/pmwiki/pmwiki.php/Manga/CodeBreaker", "/pmwiki/pmwiki.php/Manga/RanmaOneHalf", "/pmwiki/pmwiki.php/LightNovel/KyoKaraMaoh", "/pmwiki/pmwiki.php/Anime/UruseiYatsura", "/pmwiki/pmwiki.php/Manga/CromartieHighSchool", "/pmwiki/pmwiki.php/Manga/BusouRenkin", "/pmwiki/pmwiki.php/Anime/YuGiOhGX", "/pmwiki/pmwiki.php/Manga/YuGiOh", "/pmwiki/pmwiki.php/Anime/ProjectAKo", "/pmwiki/pmwiki.php/Manga/SayonaraZetsubouSensei", "/pmwiki/pmwiki.php/Manga/MahouSenseiNegima", "/pmwiki/pmwiki.php/LightNovel/HaruhiSuzumiya", "/pmwiki/pmwiki.php/Anime/ElHazardTheMagnificentWorld", "/pmwiki/pmwiki.php/Manga/InuYasha", "/pmwiki/pmwiki.php/Manga/AngelDensetsu", "/pmwiki/pmwiki.php/Manga/OmamoriHimari", "/pmwiki/pmwiki.php/LightNovel/StrawberryPanic", "/pmwiki/pmwiki.php/Manga/FushigiYuugi", "/pmwiki/pmwiki.php/Franchise/NeonGenesisEvangelion", "/pmwiki/pmwiki.php/Anime/NeonGenesisEvangelion", "/pmwiki/pmwiki.php/Anime/RebuildOfEvangelion", "/pmwiki/pmwiki.php/Manga/NeonGenesisEvangelionCampusApocalypse", "/pmwiki/pmwiki.php/Manga/MedakaBox", "/pmwiki/pmwiki.php/Manga/GakuenBabysitters", "/pmwiki/pmwiki.php/Franchise/PrettyCure", "/pmwiki/pmwiki.php/Anime/FreshPrettyCure", "/pmwiki/pmwiki.php/Anime/SuitePrettyCure", "/pmwiki/pmwiki.php/Anime/DokiDokiPrettyCure", "/pmwiki/pmwiki.php/Anime/HappinessChargePrettyCure", "/pmwiki/pmwiki.php/Manga/TheSecretNotesOfLadyKanoko", "/pmwiki/pmwiki.php/Manga/Nisekoi", "/pmwiki/pmwiki.php/Manga/WanderingSon", "/pmwiki/pmwiki.php/LightNovel/DuRaRaRa", "/pmwiki/pmwiki.php/Manga/DetectiveConan", "/pmwiki/pmwiki.php/Anime/DigimonAdventureTri", "/pmwiki/pmwiki.php/Manga/JojosBizarreAdventureStardustCrusaders", "/pmwiki/pmwiki.php/ComicBook/AmeliaRules", "/pmwiki/pmwiki.php/Film/BattleRoyale", "/pmwiki/pmwiki.php/Film/Rushmore", "/pmwiki/pmwiki.php/Film/CatchMeIfYouCan", "/pmwiki/pmwiki.php/Film/CharlieBartlett", "/pmwiki/pmwiki.php/Film/TheKarateKid2010", "/pmwiki/pmwiki.php/Film/NotAnotherTeenMovie", "/pmwiki/pmwiki.php/Literature/TheDemonHeadmaster", "/pmwiki/pmwiki.php/Literature/EthanSuspended", "/pmwiki/pmwiki.php/Literature/McAuslan", "/pmwiki/pmwiki.php/Series/StarTrekVoyager", "/pmwiki/pmwiki.php/Series/StarTrekDeepSpaceNine", "/pmwiki/pmwiki.php/Series/StarTrekEnterprise", "/pmwiki/pmwiki.php/Film/StarTrekGenerations", "/pmwiki/pmwiki.php/Series/BabylonFive", "/pmwiki/pmwiki.php/Series/RoundTheTwist", "/pmwiki/pmwiki.php/Literature/TheDemonHeadmaster", "/pmwiki/pmwiki.php/Series/SummerHeightsHigh", "/pmwiki/pmwiki.php/Series/Degrassi", "/pmwiki/pmwiki.php/Series/Degrassi", "/pmwiki/pmwiki.php/Series/KamenRiderFourze", "/pmwiki/pmwiki.php/Series/TheInbetweeners", "/pmwiki/pmwiki.php/Series/ShutUpFlowerBoyBand", "/pmwiki/pmwiki.php/VideoGame/Persona3", "/pmwiki/pmwiki.php/VideoGame/BlazBlueCrossTagBattle", "/pmwiki/pmwiki.php/VideoGame/CherryTreeHighComedyClub", "/pmwiki/pmwiki.php/Franchise/DanganRonpa", "/pmwiki/pmwiki.php/VisualNovel/Tsukihime", "/pmwiki/pmwiki.php/VisualNovel/HatofulBoyfriend", "/pmwiki/pmwiki.php/VisualNovel/HigurashiWhenTheyCry", "/pmwiki/pmwiki.php/Music/INXS"], "non_media_links": ["/pmwiki/pmwiki.php/Main/NewTransferStudent", "/pmwiki/pmwiki.php/Main/GoingNative", "/pmwiki/pmwiki.php/Main/FishOutOfWater", "/pmwiki/pmwiki.php/Main/NonUniformUniform", "/pmwiki/pmwiki.php/Main/TrappedInAnotherWorld", "/pmwiki/pmwiki.php/Main/LimitedWardrobe", "/pmwiki/pmwiki.php/Main/GoingNative", "/pmwiki/pmwiki.php/Main/StillWearingTheOldColors", "/pmwiki/pmwiki.php/Main/Stripperiffic", "/pmwiki/pmwiki.php/Main/AnimeFirst", "/pmwiki/pmwiki.php/Main/HugeSchoolgirl", "/pmwiki/pmwiki.php/Main/FaceOfAThug", "/pmwiki/pmwiki.php/Main/TrappedInAnotherWorld", "/pmwiki/pmwiki.php/Main/LimitedWardrobe", "/pmwiki/pmwiki.php/Main/WigDressAccent", "/pmwiki/pmwiki.php/Main/PaperThinDisguise", "/pmwiki/pmwiki.php/Main/FanFic", "/pmwiki/pmwiki.php/Main/TrappedInAnotherWorld", "/pmwiki/pmwiki.php/Main/ShelteredAristocrat", "/pmwiki/pmwiki.php/Main/ActionGirl", "/pmwiki/pmwiki.php/Main/Fanservice", "/pmwiki/pmwiki.php/Main/SailorFuku", "/pmwiki/pmwiki.php/Main/ImprobableWeaponUser", "/pmwiki/pmwiki.php/Main/SailorFuku", "/pmwiki/pmwiki.php/Main/LampshadeHanging", "/pmwiki/pmwiki.php/Main/GoingNative", "/pmwiki/pmwiki.php/Main/TimeTravel", "/pmwiki/pmwiki.php/Main/PortalPool", "/pmwiki/pmwiki.php/Main/ImpossiblyCoolClothes", "/pmwiki/pmwiki.php/Main/OrdinaryHighSchoolStudent", "/pmwiki/pmwiki.php/Main/TrappedInAnotherWorld", "/pmwiki/pmwiki.php/Main/AlternateUniverse", "/pmwiki/pmwiki.php/Main/DatingSim", "/pmwiki/pmwiki.php/Main/TrailersAlwaysLie", "/pmwiki/pmwiki.php/Main/AbortedArc", "/pmwiki/pmwiki.php/Main/CanonForeigner", "/pmwiki/pmwiki.php/Main/OneShotCharacter", "/pmwiki/pmwiki.php/Main/AxeCrazy", "/pmwiki/pmwiki.php/Main/ChaoticEvil", "/pmwiki/pmwiki.php/Main/PersonOfMassDestruction", "/pmwiki/pmwiki.php/Main/BigBad", "/pmwiki/pmwiki.php/Main/SailorFuku", "http://dinosbacsi.tumblr.com/post/108365622936/best-introduction-1010", "/pmwiki/pmwiki.php/Main/SailorFuku", "/pmwiki/pmwiki.php/Main/Filler", "/pmwiki/pmwiki.php/Main/FunTShirt", "/pmwiki/pmwiki.php/Main/InvertedTrope", "/pmwiki/pmwiki.php/Main/InnerCitySchool", "/pmwiki/pmwiki.php/UsefulNotes/WashingtonDC", "/pmwiki/pmwiki.php/Main/AuthorAvatar", "/pmwiki/pmwiki.php/Main/NoCommunitiesWereHarmed", "/pmwiki/pmwiki.php/UsefulNotes/WorldWarTwo", "/pmwiki/pmwiki.php/Main/RecycledINSPACE", "/pmwiki/pmwiki.php/Main/MauveShirt", "/pmwiki/pmwiki.php/Main/LiveActionAdaptation", "/pmwiki/pmwiki.php/Main/FiveManBand", "/pmwiki/pmwiki.php/Main/LampshadeHanging", "http://25.media.tumblr.com/tumblr_m5gmmasVuE1r5uoxco1_1280.jpg", "/pmwiki/pmwiki.php/Main/EffectiveImmediately", "/pmwiki/pmwiki.php/Main/TheHero", "/pmwiki/pmwiki.php/Main/SixthRanger", "/pmwiki/pmwiki.php/Main/LargeHam", "/pmwiki/pmwiki.php/Main/TheGoodOldBritishComp", "/pmwiki/pmwiki.php/Main/NonUniformUniform", "/pmwiki/pmwiki.php/Main/CulturalTranslation", "/pmwiki/pmwiki.php/Main/TransatlanticEquivalent", "/pmwiki/pmwiki.php/Main/RobotGirl", "/pmwiki/pmwiki.php/Videogame/Persona4", "/pmwiki/pmwiki.php/Main/DubNameChange", "/pmwiki/pmwiki.php/Main/LimitedWardrobe", "/pmwiki/pmwiki.php/Main/ForeignExchangeStudent", "/pmwiki/pmwiki.php/Main/FrenchJerk"]}