{"title": "Dragged by the Collar", "content": "What do you do when somebody's being stubborn or trying to excuse himself from a sticky situation? Force him into it by dragging him away by his collar, of course!\n\nGetting dragged by the collar is often used as a comedic device, most often in anime (though it does pop up in Western Animation sometimes). The \"victim\" would, more often than not, be trying to escape an embarrassing predicament (of his own doing) before another person grabs him and drags his butt off to whatever mess awaits him. The victim's loud protests and flailing of arms are optional. Small variants include getting dragged while standing (with the heels skidding on the ground instead of the butt), and stiff, outstretched arms. Sometimes, instead of the collar, characters are dragged by their cheeks, ears, arms, or legs. This is not always used for comedy, however, especially when the one being dragged away is unconscious, injured, or in severe cases, dead.\n\nSee also Necktie Leash (which is similar to this, only done for flirtatious or sexual reasons). Compare Possessive Wrist Grab where a character aggressively grabs another's wrist in a display of dominance and also The Load in which the victim actually wants to tag along, but the other characters won't let him. For a Darker and Edgier version of this trope, where the very act of dragging causes injury or even the death of the victim, see What a Drag or Ankle Drag, where the person is dragged by the ankle specifically and the person is rarely dragging them for their own good.", "url": "https://tvtropes.org/pmwiki/pmwiki.php/Main/DraggedByTheCollar", "media_links": ["/pmwiki/pmwiki.php/WesternAnimation/SpongeBobSquarePants", "/pmwiki/pmwiki.php/VideoGame/Amagami", "/pmwiki/pmwiki.php/Manga/CastleTownDandelion", "/pmwiki/pmwiki.php/Manga/KOn", "/pmwiki/pmwiki.php/Manga/MaidSama", "/pmwiki/pmwiki.php/Manga/SquidGirl", "/pmwiki/pmwiki.php/Manga/RanmaOneHalf", "/pmwiki/pmwiki.php/VisualNovel/HigurashiWhenTheyCry", "/pmwiki/pmwiki.php/Manga/FullmetalAlchemist", "/pmwiki/pmwiki.php/Anime/TheIdolmaster", "/pmwiki/pmwiki.php/Manga/ServantXService", "/pmwiki/pmwiki.php/Anime/Pokemon", "/pmwiki/pmwiki.php/Anime/SandsOfDestruction", "/pmwiki/pmwiki.php/VideoGame/SandsOfDestruction", "/pmwiki/pmwiki.php/Manga/ShokugekiNoSoma", "/pmwiki/pmwiki.php/Literature/RunWithTheWind", "/pmwiki/pmwiki.php/VideoGame/HonkaiImpact3rd", "/pmwiki/pmwiki.php/Film/IndependenceDay", "/pmwiki/pmwiki.php/Film/SupermanReturns", "/pmwiki/pmwiki.php/Film/SpiderMan2", "/pmwiki/pmwiki.php/Film/Predators", "/pmwiki/pmwiki.php/Literature/TheDresdenFiles", "/pmwiki/pmwiki.php/Theatre/Elisabeth", "/pmwiki/pmwiki.php/VideoGame/SuperSmashBros", "/pmwiki/pmwiki.php/VideoGame/Tekken", "/pmwiki/pmwiki.php/VideoGame/Tenchu", "/pmwiki/pmwiki.php/VideoGame/MetalGear", "/pmwiki/pmwiki.php/VideoGame/ArmyOfTwo", "/pmwiki/pmwiki.php/VideoGame/HeavyRain", "/pmwiki/pmwiki.php/VideoGame/SilentHill2", "/pmwiki/pmwiki.php/VideoGame/InfiniteUndiscovery", "/pmwiki/pmwiki.php/VideoGame/SuikodenI", "/pmwiki/pmwiki.php/VideoGame/SuikodenII", "/pmwiki/pmwiki.php/Webcomic/GirlGenius", "/pmwiki/pmwiki.php/Webcomic/ChibiMikuSan", "/pmwiki/pmwiki.php/Webcomic/TowerOfGod", "/pmwiki/pmwiki.php/WesternAnimation/SpongeBobSquarePants"], "non_media_links": ["/pmwiki/pmwiki.php/Main/Anime", "/pmwiki/pmwiki.php/Main/AnimatedShows", "/pmwiki/pmwiki.php/Main/RubberFace", "/pmwiki/pmwiki.php/Main/EarAche", "/pmwiki/pmwiki.php/Main/NecktieLeash", "/pmwiki/pmwiki.php/Main/PossessiveWristGrab", "/pmwiki/pmwiki.php/Main/TheLoad", "/pmwiki/pmwiki.php/Main/DarkerAndEdgier", "/pmwiki/pmwiki.php/Main/WhatADrag", "/pmwiki/pmwiki.php/Main/AnkleDrag", "/pmwiki/pmwiki.php/Main/TakingYouWithMe", "/pmwiki/pmwiki.php/Main/PlayingAgainstType", "/pmwiki/pmwiki.php/Main/ComicTrio", "/pmwiki/pmwiki.php/Main/NotADate", "/pmwiki/pmwiki.php/AudioPlay/SaintBeast", "/pmwiki/pmwiki.php/Main/RunningGag", "/pmwiki/pmwiki.php/Main/VisualPun", "/pmwiki/pmwiki.php/Main/RunningGag", "/pmwiki/pmwiki.php/Main/BigLittleBrother", "/pmwiki/pmwiki.php/Fanfic/MyHuntsmanAcademia", "/pmwiki/pmwiki.php/Main/Area51", "/pmwiki/pmwiki.php/Main/BroughtDownToNormal", "/pmwiki/pmwiki.php/Main/BadassLongcoat", "https://www.youtube.com/watch?v=x_QRj-OUyvQ", "/pmwiki/pmwiki.php/Main/BoringButPractical", "/pmwiki/pmwiki.php/Main/DownloadableContent", "/pmwiki/pmwiki.php/Main/TheProfiler", "/pmwiki/pmwiki.php/Main/NamesToRunAwayFromReallyFast", "/pmwiki/pmwiki.php/Main/VideoGame", "/pmwiki/pmwiki.php/Main/LampshadeHanging", "/pmwiki/pmwiki.php/Main/EarAche", "/pmwiki/pmwiki.php/Main/FetchQuest", "http://www.girlgeniusonline.com/comic.php?date=20110701", "/pmwiki/pmwiki.php/Main/FriendToAllChildren", "/pmwiki/pmwiki.php/WebAnimation/RWBY", "/pmwiki/pmwiki.php/Recap/SpongeBobSquarePantsS6E20NoHatForPatToyStoreOfDoom"]}