{"title": "Marionette Master", "content": "This guy doesn't fight via his own power; he has an army of Perverse Puppets\u2014that he controls via strings, magic, or advanced technology\u2014to do it for him. Particularly sadistic ones can also make People Puppets. See also Evil Puppeteer.\n\nA Subtrope of Art Attacker and The Beastmaster. May overlap with Robot Master or Wicked Toymaker.\n\nNot to be confused with Puppet Fighter, a metaphor to describe a certain type of gameplay.", "url": "https://tvtropes.org/pmwiki/pmwiki.php/Main/MarionetteMaster", "media_links": ["/pmwiki/pmwiki.php/VideoGame/Touhou", "/pmwiki/pmwiki.php/Manga/Naruto", "/pmwiki/pmwiki.php/Manga/RurouniKenshin", "/pmwiki/pmwiki.php/Manga/Trigun", "/pmwiki/pmwiki.php/Manga/Hellsing", "/pmwiki/pmwiki.php/Manga/MahouSenseiNegima", "/pmwiki/pmwiki.php/Manga/GetBackers", "/pmwiki/pmwiki.php/Manga/ZeroSevenGhost", "/pmwiki/pmwiki.php/Manga/Bleach", "/pmwiki/pmwiki.php/Manga/OnePiece", "/pmwiki/pmwiki.php/Manga/KarakuriCircus", "/pmwiki/pmwiki.php/LightNovel/ShakuganNoShana", "/pmwiki/pmwiki.php/Manga/MagicalGirlLyricalNanohaVivid", "/pmwiki/pmwiki.php/Manga/PandoraHearts", "/pmwiki/pmwiki.php/Manga/Inuyasha", "/pmwiki/pmwiki.php/Manga/Genzo", "/pmwiki/pmwiki.php/Anime/SaberMarionetteJ", "/pmwiki/pmwiki.php/Anime/TigerAndBunny", "/pmwiki/pmwiki.php/Anime/YuGiOhZEXAL", "/pmwiki/pmwiki.php/Franchise/TheDCU", "/pmwiki/pmwiki.php/ComicBook/TeenTitans", "/pmwiki/pmwiki.php/ComicBook/Superman", "/pmwiki/pmwiki.php/ComicBook/Hawkman", "/pmwiki/pmwiki.php/ComicBook/Wanted", "/pmwiki/pmwiki.php/ComicBook/TopTen", "/pmwiki/pmwiki.php/ComicBook/TheBeano", "/pmwiki/pmwiki.php/Film/SmallSoldiers", "/pmwiki/pmwiki.php/WesternAnimation/Coraline", "/pmwiki/pmwiki.php/Film/PuppetMaster", "/pmwiki/pmwiki.php/Film/TalesFromTheHood", "/pmwiki/pmwiki.php/Creator/SeananMcGuire", "/pmwiki/pmwiki.php/Literature/VelveteenVs", "/pmwiki/pmwiki.php/Series/KamenRiderDecade", "/pmwiki/pmwiki.php/Series/KaizokuSentaiGokaiger", "/pmwiki/pmwiki.php/Series/TheWildWildWest", "/pmwiki/pmwiki.php/VideoGame/Neverwinter", "/pmwiki/pmwiki.php/VideoGame/MetalGearGhostBabel", "/pmwiki/pmwiki.php/VideoGame/MetalGearSolid4", "/pmwiki/pmwiki.php/VideoGame/Onmyoji", "/pmwiki/pmwiki.php/VideoGame/FinalFantasyX", "/pmwiki/pmwiki.php/VideoGame/ShadowHearts", "/pmwiki/pmwiki.php/VideoGame/Touhou", "/pmwiki/pmwiki.php/Franchise/TheLegendOfZelda", "/pmwiki/pmwiki.php/VideoGame/TheLegendOfZeldaTheWindWaker", "/pmwiki/pmwiki.php/VideoGame/TheLegendOfZeldaTwilightPrincess", "/pmwiki/pmwiki.php/VideoGame/ArcanaHeart", "/pmwiki/pmwiki.php/VideoGame/FinalFantasyXI", "/pmwiki/pmwiki.php/VideoGame/BlazBlue", "/pmwiki/pmwiki.php/VideoGame/TheWorldEndsWithYou", "/pmwiki/pmwiki.php/VideoGame/FinalFantasyIVTheAfterYears", "/pmwiki/pmwiki.php/VideoGame/OgreBattle", "/pmwiki/pmwiki.php/VideoGame/RhapsodyAMusicalAdventure", "/pmwiki/pmwiki.php/VideoGame/PsiOpsTheMindgateConspiracy", "/pmwiki/pmwiki.php/VideoGame/ShiningForce", "/pmwiki/pmwiki.php/VideoGame/SoulNomadAndTheWorldEaters", "/pmwiki/pmwiki.php/VideoGame/Mabinogi", "/pmwiki/pmwiki.php/VideoGame/ManaKhemiaAlchemistsOfAlRevis", "/pmwiki/pmwiki.php/VideoGame/FireEmblemFates", "/pmwiki/pmwiki.php/VideoGame/BlueReflection", "/pmwiki/pmwiki.php/Webcomic/Homestuck", "/pmwiki/pmwiki.php/Webcomic/Erfworld"], "non_media_links": ["/pmwiki/pmwiki.php/Main/SugarApocalypse", "/pmwiki/pmwiki.php/Main/PerversePuppet", "/pmwiki/pmwiki.php/Main/RazorFloss", "/pmwiki/pmwiki.php/Main/AWizardDidIt", "/pmwiki/pmwiki.php/Main/AppliedPhlebotinum", "/pmwiki/pmwiki.php/Main/LivingDollCollector", "/pmwiki/pmwiki.php/Main/PeoplePuppets", "/pmwiki/pmwiki.php/Main/EvilPuppeteer", "/pmwiki/pmwiki.php/Main/Subtrope", "/pmwiki/pmwiki.php/Main/ArtAttacker", "/pmwiki/pmwiki.php/Main/TheBeastmaster", "/pmwiki/pmwiki.php/Main/RobotMaster", "/pmwiki/pmwiki.php/Main/WickedToymaker", "/pmwiki/pmwiki.php/Main/PuppeteerParasite", "/pmwiki/pmwiki.php/Main/MarionetteMotion", "/pmwiki/pmwiki.php/Main/PuppetFighter", "/pmwiki/pmwiki.php/Main/CoolOldLady", "/pmwiki/pmwiki.php/Main/HeelFaceTurn", "/pmwiki/pmwiki.php/Main/PeoplePuppets", "/pmwiki/pmwiki.php/Main/ClockPunk", "/pmwiki/pmwiki.php/Main/GiantRobot", "/pmwiki/pmwiki.php/Main/RazorFloss", "/pmwiki/pmwiki.php/Main/PeoplePuppet", "/pmwiki/pmwiki.php/Main/IHaveManyNames", "/pmwiki/pmwiki.php/Main/OurVampiresAreDifferent", "/pmwiki/pmwiki.php/Main/PeoplePuppets", "/pmwiki/pmwiki.php/Main/CooldownHug", "/pmwiki/pmwiki.php/Main/BarrierWarrior", "/pmwiki/pmwiki.php/Main/PeoplePuppets", "/pmwiki/pmwiki.php/Main/RazorFloss", "/pmwiki/pmwiki.php/Main/PeoplePuppets", "/pmwiki/pmwiki.php/Main/Golem", "/pmwiki/pmwiki.php/Main/DittoFighter", "/pmwiki/pmwiki.php/Main/CrystalDragonJesus", "/pmwiki/pmwiki.php/Main/MarionetteMaster", "/pmwiki/pmwiki.php/Main/MarionetteMotion", "/pmwiki/pmwiki.php/Main/CrazyPrepared", "/pmwiki/pmwiki.php/Main/UglyCute", "/pmwiki/pmwiki.php/Main/MundaneUtility", "/pmwiki/pmwiki.php/Comicbook/Supergirl", "/pmwiki/pmwiki.php/Comicbook/TheFlash", "/pmwiki/pmwiki.php/Videogame/DCUniverseOnline", "/pmwiki/pmwiki.php/Comicbook/Convergence", "/pmwiki/pmwiki.php/Main/Expy", "/pmwiki/pmwiki.php/Comicbook/XMen", "/pmwiki/pmwiki.php/Comicbook/Firestorm", "/pmwiki/pmwiki.php/Comicbook/Batgirl", "/pmwiki/pmwiki.php/Main/CaptainErsatz", "/pmwiki/pmwiki.php/FanFic/LupineTree", "/pmwiki/pmwiki.php/Main/Tokusatsu", "/pmwiki/pmwiki.php/Main/PowerCopying", "https://www.youtube.com/watch?v=bKtvDv7eykg", "/pmwiki/pmwiki.php/Main/KoreanPopMusic", "/pmwiki/pmwiki.php/Main/MarionetteMaster", "/pmwiki/pmwiki.php/Main/WordSaladTitle", "https://www.youtube.com/watch?v=5tLooPlf2Sw", "/pmwiki/pmwiki.php/Main/PeoplePuppets", "/pmwiki/pmwiki.php/Main/PeoplePuppets", "/pmwiki/pmwiki.php/Main/MeaningfulName", "/pmwiki/pmwiki.php/Main/ThemeNaming", "/pmwiki/pmwiki.php/Main/MundaneUtility", "/pmwiki/pmwiki.php/Main/ThatOneBoss", "/pmwiki/pmwiki.php/Main/PerversePuppet", "/pmwiki/pmwiki.php/Main/SoulJar", "/pmwiki/pmwiki.php/Main/MeatPuppet", "/pmwiki/pmwiki.php/Videogame/TalesOfTheAbyss", "/pmwiki/pmwiki.php/Main/CuteBruiser", "/pmwiki/pmwiki.php/Main/CuteGhostGirl", "/pmwiki/pmwiki.php/Main/SealedEvilInATeddyBear", "/pmwiki/pmwiki.php/Main/Wutai", "/pmwiki/pmwiki.php/Main/EyeBeams", "/pmwiki/pmwiki.php/Main/MagicWand", "/pmwiki/pmwiki.php/Main/DemonicDummy", "/pmwiki/pmwiki.php/Main/Flashstep", "/pmwiki/pmwiki.php/Main/TeleportSpam", "/pmwiki/pmwiki.php/Main/CrazyAwesome", "/pmwiki/pmwiki.php/Main/ParanoiaFuel", "/pmwiki/pmwiki.php/Main/AIs"]}