{"title": "Large Ham Radio", "content": "Radio, especially the amateur variety, will always attract a certain type of DJ/Announcer, namely a Large Ham. At least in fiction.\n\nAnyone put in front of a radio mic, even if he's never seen one before, will instantly switch into a confident DJ-persona, complete with nickname, Catch Phrases and a smooth baritone voice. Otherwise, they might become an abrasive Dumbass DJ or Shock Jock. Whatever style he chooses, there won't be a second's hesitation, confusion, Dead Air or any other problems you might expect of a Na\u00efve Newcomer.\n\nIf it's ham radio they're getting into, it's very likely they'll also immediately turn into a Soapbox Sadie Conspiracy Theorist convinced that the government wants to shut them down.\n\nAnother common variant, more popular in the United Kingdom, is the Tony Blackburn-esque (probably better known to younger generations as Smashie and Nicey-esque) cheesy 1970s pop DJ.\n\nNot to be confused with Radio Voice. Closely related to Danger Deadpan, a similar effect caused by speaking over an aeroplane intercom. Compare Large Ham Announcer.", "url": "https://tvtropes.org/pmwiki/pmwiki.php/Main/LargeHamRadio", "media_links": ["/pmwiki/pmwiki.php/VideoGame/Fallout3", "/pmwiki/pmwiki.php/Radio/TonyBlackburn", "/pmwiki/pmwiki.php/Series/HarryEnfieldAndChums", "/pmwiki/pmwiki.php/VisualNovel/OretachiNiTsubasaWaNai", "/pmwiki/pmwiki.php/Creator/TomokazuSugita", "/pmwiki/pmwiki.php/Film/HighSchoolMusical", "/pmwiki/pmwiki.php/Film/HarryPotter", "/pmwiki/pmwiki.php/Film/PumpUpTheVolume", "/pmwiki/pmwiki.php/Creator/RobinWilliams", "/pmwiki/pmwiki.php/Film/GoodMorningVietnam", "/pmwiki/pmwiki.php/Film/Grease", "/pmwiki/pmwiki.php/Series/TopOfThePops", "/pmwiki/pmwiki.php/Series/Bluestone42", "/pmwiki/pmwiki.php/Film/JMenForever", "/pmwiki/pmwiki.php/Film/ReservoirDogs", "/pmwiki/pmwiki.php/Creator/StevenWright", "/pmwiki/pmwiki.php/Literature/PhulesCompany", "/pmwiki/pmwiki.php/Literature/HarryPotter", "/pmwiki/pmwiki.php/Literature/HarryPotterAndTheDeathlyHallows", "/pmwiki/pmwiki.php/Series/HowIMetYourMother", "/pmwiki/pmwiki.php/Series/MalcolmInTheMiddle", "/pmwiki/pmwiki.php/Series/ThirdRockFromTheSun", "/pmwiki/pmwiki.php/Series/MASH", "/pmwiki/pmwiki.php/Series/QuantumLeap", "/pmwiki/pmwiki.php/Series/WKRPInCincinnati", "/pmwiki/pmwiki.php/Series/Psych", "/pmwiki/pmwiki.php/Series/KamenRiderGaim", "/pmwiki/pmwiki.php/Series/Frasier", "/pmwiki/pmwiki.php/Music/PeterGabriel", "/pmwiki/pmwiki.php/Music/DavidBowie", "/pmwiki/pmwiki.php/Music/Lodger", "/pmwiki/pmwiki.php/Music/MyChemicalRomance", "/pmwiki/pmwiki.php/Music/BlueOysterCult", "/pmwiki/pmwiki.php/Creator/HowardStern", "/pmwiki/pmwiki.php/Music/TheBigBopper", "/pmwiki/pmwiki.php/Series/Thunderbirds", "/pmwiki/pmwiki.php/Radio/TheSpaceGypsyAdventures", "/pmwiki/pmwiki.php/Radio/TonyBlackburn", "/pmwiki/pmwiki.php/VideoGame/Fallout3", "/pmwiki/pmwiki.php/VideoGame/FalloutNewVegas", "/pmwiki/pmwiki.php/VideoGame/Fallout4", "/pmwiki/pmwiki.php/VideoGame/JetSetRadio", "/pmwiki/pmwiki.php/VideoGame/SilentHillDownpour", "/pmwiki/pmwiki.php/VideoGame/GrandTheftAutoViceCity", "/pmwiki/pmwiki.php/Radio/GTARadio", "/pmwiki/pmwiki.php/WesternAnimation/TheSimpsons", "/pmwiki/pmwiki.php/WesternAnimation/TheFairlyOddparents", "/pmwiki/pmwiki.php/WesternAnimation/PhineasAndFerb", "/pmwiki/pmwiki.php/WesternAnimation/FamilyGuy", "/pmwiki/pmwiki.php/Creator/NPR", "/pmwiki/pmwiki.php/Creator/HowardStern", "/pmwiki/pmwiki.php/Film/SixteenCandles", "/pmwiki/pmwiki.php/Film/AnimalHouse", "/pmwiki/pmwiki.php/Film/Philadelphia", "/pmwiki/pmwiki.php/WesternAnimation/Sealab2021", "/pmwiki/pmwiki.php/WesternAnimation/HeyArnold", "/pmwiki/pmwiki.php/WesternAnimation/GarfieldAndFriends", "/pmwiki/pmwiki.php/Series/RowanAndMartinsLaughIn", "/pmwiki/pmwiki.php/Film/AmericanGraffiti", "/pmwiki/pmwiki.php/WesternAnimation/ScoobyDoo", "/pmwiki/pmwiki.php/Radio/AmericanTop40", "/pmwiki/pmwiki.php/Creator/NPR", "/pmwiki/pmwiki.php/WesternAnimation/FamilyGuy"], "non_media_links": ["/pmwiki/pmwiki.php/Main/Radio", "/pmwiki/pmwiki.php/Main/CollegeRadio", "/pmwiki/pmwiki.php/Main/LargeHam", "/pmwiki/pmwiki.php/Main/CatchPhrase", "/pmwiki/pmwiki.php/Main/DangerDeadpan", "/pmwiki/pmwiki.php/Main/BadassBaritone", "/pmwiki/pmwiki.php/Main/DumbassDJ", "/pmwiki/pmwiki.php/Main/ShockJock", "/pmwiki/pmwiki.php/Main/DeadAir", "/pmwiki/pmwiki.php/Main/NaiveNewcomer", "/pmwiki/pmwiki.php/Main/SoapboxSadie", "/pmwiki/pmwiki.php/Main/ConspiracyTheorist", "/pmwiki/pmwiki.php/Main/SeriousBusiness", "/pmwiki/pmwiki.php/Main/WeirdAlEffect", "/pmwiki/pmwiki.php/Main/RadioVoice", "/pmwiki/pmwiki.php/Main/DangerDeadpan", "/pmwiki/pmwiki.php/Main/LargeHamAnnouncer", "/pmwiki/pmwiki.php/Main/SubvertedTrope", "https://www.youtube.com/watch?v=gh5xu35bAxA", "/pmwiki/pmwiki.php/Main/VoiceOfTheResistance", "/pmwiki/pmwiki.php/Main/NatBandstand", "/pmwiki/pmwiki.php/Main/EvilPlan", "/pmwiki/pmwiki.php/Main/SexDrugsAndRockAndRoll", "/pmwiki/pmwiki.php/Main/VoiceOfTheResistance", "/pmwiki/pmwiki.php/Main/CollegeRadio", "/pmwiki/pmwiki.php/Main/CloudCuckoolander", "/pmwiki/pmwiki.php/Main/EarWorm", "/pmwiki/pmwiki.php/Main/TheScreenSavers", "/pmwiki/pmwiki.php/Main/ShoutOut", "/pmwiki/pmwiki.php/Main/DumbassDJ", "/pmwiki/pmwiki.php/Main/SwappedRoles", "https://www.youtube.com/watch?v=GW2YQFlILFo", "/pmwiki/pmwiki.php/Main/BuccaneerBroadcaster", "/pmwiki/pmwiki.php/Main/SpaceStation", "/pmwiki/pmwiki.php/Main/TooDumbToLive", "/pmwiki/pmwiki.php/Main/AxCrazy", "/pmwiki/pmwiki.php/Main/SplitPersonality", "/pmwiki/pmwiki.php/Main/FunnySchizophrenia", "/pmwiki/pmwiki.php/Main/UpToEleven", "/pmwiki/pmwiki.php/Main/ItMakesSenseInContext", "/pmwiki/pmwiki.php/Main/JiveTurkey", "/pmwiki/pmwiki.php/WebAnimation/HomestarRunner", "/pmwiki/pmwiki.php/WebAnimation/StrongBadEmail", "/pmwiki/pmwiki.php/Main/VocalDissonance", "/pmwiki/pmwiki.php/Podcast/TheOrbitingHumanCircusOfTheAir", "/pmwiki/pmwiki.php/Main/InteractiveNarrator", "/pmwiki/pmwiki.php/Podcast/ItMakesASound", "/pmwiki/pmwiki.php/Main/StylisticSuck", "/pmwiki/pmwiki.php/Main/DumbassDJ", "/pmwiki/pmwiki.php/Main/ExecutiveMeddling", "/pmwiki/pmwiki.php/Main/CrossesTheLineTwice", "/pmwiki/pmwiki.php/Main/OnceAnEpisode", "/pmwiki/pmwiki.php/Main/InAWorld", "/pmwiki/pmwiki.php/Main/UpToEleven", "/pmwiki/pmwiki.php/Main/ColdHam", "/pmwiki/pmwiki.php/Main/TwoDecadesBehind"]}