{"title": "Bathroom Brawl", "content": "\"I don't remember who threw the first punch, but it all went to shit after that.\"\n\nBathrooms are intended for people to... uh, do their business. However, one or more characters decide that it's the perfect place to duke it out. A bathroom brawl can occur in either a public bathroom or a private one, although it is more common for fights to happen in public restrooms. Locker rooms also apply.\n\nCommon weapons/attacks that be used in a bathroom brawl may include, but are not limited to: Swirlies, feces or urine, toilet paper, the sink, the mirror, the stall doors, etc.\n\nSimilar to Camping a Crapper, although the difference between this trope and Camping a Crapper is that the latter is typically an attack that is planned, while a bathroom brawl does not have to be organized in advance. Often times, it can start out as a simple conversation or an argument, and then build up into a huge fight.\n\nCan overlap with Toilet Horror if the fight gets incredibly violent or the characters fight something or someone horrifying. If someone ends up getting killed in a bathroom brawl, then see The Can Kicked Him.", "url": "https://tvtropes.org/pmwiki/pmwiki.php/Main/BathroomBrawl", "media_links": ["/pmwiki/pmwiki.php/Film/TheWarriors", "/pmwiki/pmwiki.php/Anime/Canaan", "/pmwiki/pmwiki.php/Anime/PantyAndStockingWithGarterbelt", "/pmwiki/pmwiki.php/ComicBook/SpyBoy", "/pmwiki/pmwiki.php/ComicBook/Watchmen", "/pmwiki/pmwiki.php/WesternAnimation/BeeMovie", "/pmwiki/pmwiki.php/Film/AustinPowersInternationalManOfMystery", "/pmwiki/pmwiki.php/Film/TheBourneUltimatum", "/pmwiki/pmwiki.php/Film/TheCableGuy", "/pmwiki/pmwiki.php/Film/CasinoRoyale2006", "/pmwiki/pmwiki.php/Film/JamesBond", "/pmwiki/pmwiki.php/Film/DeathGrip", "/pmwiki/pmwiki.php/Film/JackReacher", "/pmwiki/pmwiki.php/Film/KillBill", "/pmwiki/pmwiki.php/Film/TheManFromUNCLE2015", "/pmwiki/pmwiki.php/Film/MissionImpossibleFallout", "/pmwiki/pmwiki.php/Film/OurManFlint", "/pmwiki/pmwiki.php/Film/TrueLies", "/pmwiki/pmwiki.php/Film/TrueRomance", "/pmwiki/pmwiki.php/Film/TheWarriors", "/pmwiki/pmwiki.php/Film/TheWorldsEnd", "/pmwiki/pmwiki.php/Literature/EndersGame", "/pmwiki/pmwiki.php/Literature/HarryPotter", "/pmwiki/pmwiki.php/Literature/HarryPotterAndThePhilosophersStone", "/pmwiki/pmwiki.php/Literature/HarryPotterAndTheHalfBloodPrince", "/pmwiki/pmwiki.php/Film/HarryPotterAndTheHalfBloodPrince", "/pmwiki/pmwiki.php/Creator/TomFelton", "/pmwiki/pmwiki.php/Creator/DanielRadcliffe", "/pmwiki/pmwiki.php/Literature/Nightside", "/pmwiki/pmwiki.php/Literature/PercyJacksonAndTheOlympians", "/pmwiki/pmwiki.php/Series/BurnNotice", "/pmwiki/pmwiki.php/Series/ChillingAdventuresOfSabrina", "/pmwiki/pmwiki.php/Series/WKRPInCincinnati", "/pmwiki/pmwiki.php/VideoGame/Bully", "/pmwiki/pmwiki.php/VideoGame/SuperPaperMario", "/pmwiki/pmwiki.php/VideoGame/Uncharted3DrakesDeception", "/pmwiki/pmwiki.php/VideoGame/Yakuza0", "/pmwiki/pmwiki.php/Series/CobraKai", "/pmwiki/pmwiki.php/WesternAnimation/OKKOLetsBeHeroes", "/pmwiki/pmwiki.php/WesternAnimation/RickAndMorty", "/pmwiki/pmwiki.php/WesternAnimation/SouthPark", "/pmwiki/pmwiki.php/Website/YouTube"], "non_media_links": ["/pmwiki/pmwiki.php/Main/Swirlie", "/pmwiki/pmwiki.php/Main/DungFu", "/pmwiki/pmwiki.php/Main/ExcrementStatement", "/pmwiki/pmwiki.php/Main/TaeKwonDoor", "/pmwiki/pmwiki.php/Main/CampingACrapper", "/pmwiki/pmwiki.php/Main/ToiletHorror", "/pmwiki/pmwiki.php/Main/TheCanKickedHim", "/pmwiki/pmwiki.php/Main/ManchurianAgent", "/pmwiki/pmwiki.php/Main/TeenSuperspy", "/pmwiki/pmwiki.php/FanFic/ByBakerStreetStationISatDownAndWept", "/pmwiki/pmwiki.php/Main/BlatantLies", "/pmwiki/pmwiki.php/Main/DownplayedTrope", "/pmwiki/pmwiki.php/Fanfic/PersonaEG", "/pmwiki/pmwiki.php/Main/SignatureScene", "/pmwiki/pmwiki.php/Main/ImprobableWeaponUser", "/pmwiki/pmwiki.php/Main/PlayedForLaughs", "/pmwiki/pmwiki.php/Main/BondGunBarrel", "/pmwiki/pmwiki.php/Main/Mooks", "https://www.youtube.com/watch?v=cdB6c3n8RAw", "/pmwiki/pmwiki.php/Main/UndercoverAsLovers", "/pmwiki/pmwiki.php/Main/PercussiveTherapy", "/pmwiki/pmwiki.php/Main/TheCanKickedHim", "/pmwiki/pmwiki.php/Main/BigBad", "/pmwiki/pmwiki.php/Main/JackBauerInterrogationTechnique", "/pmwiki/pmwiki.php/Main/ThereIsNoKillLikeOverkill", "/pmwiki/pmwiki.php/Main/RoboticReveal", "/pmwiki/pmwiki.php/Main/GangOfBullies", "/pmwiki/pmwiki.php/Main/FullFrontalAssault", "/pmwiki/pmwiki.php/Main/ThatCameOutWrong", "/pmwiki/pmwiki.php/Main/TheStarscream", "/pmwiki/pmwiki.php/Main/ARareSentence", "/pmwiki/pmwiki.php/Wrestling/WCW", "/pmwiki/pmwiki.php/Main/GimmickMatches", "/pmwiki/pmwiki.php/Wrestling/ChrisBenoit", "/pmwiki/pmwiki.php/Wrestling/KevinSullivan", "/pmwiki/pmwiki.php/Wrestling/MikeShaw", "/pmwiki/pmwiki.php/Wrestling/WWERaw", "/pmwiki/pmwiki.php/Main/GarbageWrestler", "http://www.wrestling-titles.com/wwe/wwf-wm.html", "/pmwiki/pmwiki.php/Wrestling/Ivory", "/pmwiki/pmwiki.php/Wrestling/TerriPoch", "/pmwiki/pmwiki.php/Main/ModestyTowel", "/pmwiki/pmwiki.php/Wrestling/Jacqueline", "/pmwiki/pmwiki.php/Main/BarBrawl", "/pmwiki/pmwiki.php/Main/EscalatingBrawl", "/pmwiki/pmwiki.php/Main/GiantMook", "/pmwiki/pmwiki.php/Main/IronButtMonkey", "/pmwiki/pmwiki.php/Main/DestinationDefenestration", "/pmwiki/pmwiki.php/WebAnimation/CyanideAndHappiness", "https://m.youtube.com/watch?v=e2nGhmukF5s", "/pmwiki/pmwiki.php/Main/ToiletTeleportation", "/pmwiki/pmwiki.php/Recap/SouthParkS19E1StunningAndBrave", "/pmwiki/pmwiki.php/Main/PoliticalCorrectnessGoneMad"]}