{"title": "Eldritch Abomination", "content": "\"Here, on the horizon, was everything Gideon did not know.\"\n\nThe Alien. The Other. The Inconceivable. The Eldritch Abomination is a type of creature defined by its disregard for the natural laws of the universe as we understand them. They are grotesque mockeries of reality beyond comprehension whose disturbing otherness cannot be encompassed in any mortal tongue. Humans suffer Brown Note or Go Mad from the Revelation effects just from witnessing their Alien Geometries. Reality itself warps around them. Any rules that they do follow are beyond our understanding, as are what motives they might have for any of their actions.\n\nNative to the Cosmic Horror Story genre popularized by H. P. Lovecraft, the Eldritch Abomination has become a mainstay of horror and fantasy works, along with numerous others that derive inspiration from Lovecraft. They are often used as a Greater-Scope Villain, Outside-Context Problem, Mad God, Evil God or Sealed Evil in a Can. If it's truely a faithful alien however, it shouldn't even be \"evil\" in the typical sense. As they are defined by existing outside reality as we conceive it, most also come from somewhere beyond the stars or before the dawn of time or outside our universe.\n\nPhysically, the Eldritch Abomination is only defined by seeming somehow \u0093off\u0094, hinting at their incomprehensible nature. They can range from humanoid to animalistic to physically impossible to inconceivably bizarre. However, common physical characteristics include similarities to internal organs, genitalia, animals with tentacles, or celestial bodies.\n\nThe power of these beings can greatly vary. Some of which can be defeated by mortals, usually via a special weapon specifically meant to kill them, some of which are more powerful than gods, but are often still able to be defeated. In the Cosmic Horror Story genre, however, these beings are usually unbeatable, or are technically beatable, but will result in a Pyrrhic Victory with an incredible cost.\n\nSubtrope of Our Monsters Are Different and Our Monsters Are Weird. Though note that a monster being really powerful, weird or ugly is not, in and of itself, an example of this trope. The monster must break the established internal logic of the work, possibly causing Go Mad from the Revelation.\n\nFor specific storylines involving Eldritch Abominations, see the Did You Just Index Cthulhu? page. Compare with God of Evil, The Old Gods, Paradox Person, and Starfish Aliens. When humans are Eldritch Abominations, that's Humans Are Cthulhu. Sub-Trope of Brown Note Being, since eldritch or abomination doesn't describe every creature which causes a Brown Note, nor does every Eldritch Abomination cause one (though it is common for them).\n\nDo not confuse this with Complete Monster, which is more about evil than (physical) monstrousness, especially since a Complete Monster isn't necessarily a literal monster. However, an Eldritch Abomination who has clear agency and is sufficiently heinous by the standards of the story can qualify as a Complete Monster.\n\nThanks to the nature of this trope, potential Real Life examples are very vague and questionable at best. So No Real Life Examples, Please!", "url": "https://tvtropes.org/pmwiki/pmwiki.php/Main/Eldritchabomination", "media_links": ["/pmwiki/pmwiki.php/TabletopGame/MagicTheGathering", "/pmwiki/pmwiki.php/Creator/KurtBusiek", "/pmwiki/pmwiki.php/ComicBook/AstroCity", "/pmwiki/pmwiki.php/Creator/HPLovecraft", "/pmwiki/pmwiki.php/Literature/LoneWolf", "/pmwiki/pmwiki.php/Literature/WelcomeToNightVale", "/pmwiki/pmwiki.php/Literature/TheCallOfCthulhu", "/pmwiki/pmwiki.php/VideoGame/LEGOUniverse", "/pmwiki/pmwiki.php/Literature/IHaveNoMouthAndIMustScream", "/pmwiki/pmwiki.php/Manga/DragonBallZ", "/pmwiki/pmwiki.php/Creator/MarvelComics", "/pmwiki/pmwiki.php/Creator/DCComics", "/pmwiki/pmwiki.php/Theatre/PeerGynt", "/pmwiki/pmwiki.php/Ride/AltonTowers", "/pmwiki/pmwiki.php/Toys/Bionicle", "/pmwiki/pmwiki.php/Franchise/Transformers", "/pmwiki/pmwiki.php/WesternAnimation/TransformersPrime", "/pmwiki/pmwiki.php/Literature/TransformersExodus", "/pmwiki/pmwiki.php/Film/TransformersRevengeOfTheFallen", "/pmwiki/pmwiki.php/Toys/Figma", "/pmwiki/pmwiki.php/LightNovel/HaiyoreNyarkoSan", "/pmwiki/pmwiki.php/Anime/PuellaMagiMadokaMagica", "/pmwiki/pmwiki.php/Franchise/CthulhuMythos", "/pmwiki/pmwiki.php/VisualNovel/Demonbane", "/pmwiki/pmwiki.php/VisualNovel/HatofulBoyfriend", "/pmwiki/pmwiki.php/Franchise/Nasuverse", "/pmwiki/pmwiki.php/Literature/AngelNotes", "/pmwiki/pmwiki.php/VisualNovel/FateStayNight", "/pmwiki/pmwiki.php/VideoGame/FateGrandOrder", "/pmwiki/pmwiki.php/Literature/ArsGoetia", "/pmwiki/pmwiki.php/Franchise/CthulhuMythos", "/pmwiki/pmwiki.php/VisualNovel/SayaNoUta", "/pmwiki/pmwiki.php/VisualNovel/ShikkokuNoSharnoth", "/pmwiki/pmwiki.php/VisualNovel/TheUncleWhoWorksForNintendo", "/pmwiki/pmwiki.php/VisualNovel/WeKnowTheDevil", "/pmwiki/pmwiki.php/VisualNovel/MayITakeYourOrder", "/pmwiki/pmwiki.php/Webcomic/GarnetAndGure", "/pmwiki/pmwiki.php/Webcomic/BoxerHockey", "/pmwiki/pmwiki.php/VideoGame/SimCity", "/pmwiki/pmwiki.php/VideoGame/TheSims", "/pmwiki/pmwiki.php/Creator/ElectronicArts", "/pmwiki/pmwiki.php/Music/LemonDemon", "/pmwiki/pmwiki.php/WesternAnimation/SongInTheSky", "/pmwiki/pmwiki.php/VideoGame/ClockTower", "/pmwiki/pmwiki.php/VideoGame/EarthBound"], "non_media_links": ["/pmwiki/pmwiki.php/Main/SurrealHorror", "/pmwiki/pmwiki.php/Main/YouCannotGraspTheTrueForm", "/pmwiki/pmwiki.php/Main/BrownNote", "/pmwiki/pmwiki.php/Main/GoMadFromTheRevelation", "/pmwiki/pmwiki.php/Main/AlienGeometries", "/pmwiki/pmwiki.php/Main/RealityWarper", "/pmwiki/pmwiki.php/Main/BlueAndOrangeMorality", "/pmwiki/pmwiki.php/Main/CosmicHorrorStory", "/pmwiki/pmwiki.php/Main/Horror", "/pmwiki/pmwiki.php/Main/Fantasy", "/pmwiki/pmwiki.php/Main/Mythopoeia", "/pmwiki/pmwiki.php/Main/GreaterScopeVillain", "/pmwiki/pmwiki.php/Main/OutsideContextProblem", "/pmwiki/pmwiki.php/Main/MadGod", "/pmwiki/pmwiki.php/Main/GodOfEvil", "/pmwiki/pmwiki.php/Main/SealedEvilInACan", "/pmwiki/pmwiki.php/Main/AboveGoodAndEvil", "/pmwiki/pmwiki.php/Main/TimeAbyss", "/pmwiki/pmwiki.php/Main/EldritchLocation", "/pmwiki/pmwiki.php/Main/UncannyValley", "/pmwiki/pmwiki.php/Main/YouCannotGraspTheTrueForm", "/pmwiki/pmwiki.php/Main/HumanoidAbomination", "/pmwiki/pmwiki.php/Main/AnimalisticAbomination", "/pmwiki/pmwiki.php/Main/AlienGeometries", "/pmwiki/pmwiki.php/Main/MindScrew", "/pmwiki/pmwiki.php/Main/BodyHorror", "/pmwiki/pmwiki.php/Main/FreudWasRight", "/pmwiki/pmwiki.php/Main/TentacledTerror", "/pmwiki/pmwiki.php/Main/CelestialBody", "/pmwiki/pmwiki.php/Main/DidYouJustPunchOutCthulhu", "/pmwiki/pmwiki.php/Main/WeaponOfXSlaying", "/pmwiki/pmwiki.php/Main/AboveTheGods", "/pmwiki/pmwiki.php/Main/CosmicHorrorStory", "/pmwiki/pmwiki.php/Main/PyrrhicVictory", "/pmwiki/pmwiki.php/Main/OurMonstersAreDifferent", "/pmwiki/pmwiki.php/Main/OurMonstersAreWeird", "/pmwiki/pmwiki.php/Main/GoMadFromTheRevelation", "/pmwiki/pmwiki.php/Main/DidYouJustIndexCthulhu", "/pmwiki/pmwiki.php/Main/GodOfEvil", "/pmwiki/pmwiki.php/Main/TheOldGods", "/pmwiki/pmwiki.php/Main/ParadoxPerson", "/pmwiki/pmwiki.php/Main/StarfishAliens", "/pmwiki/pmwiki.php/Main/HumansAreCthulhu", "/pmwiki/pmwiki.php/Main/SubTrope", "/pmwiki/pmwiki.php/Main/BrownNoteBeing", "/pmwiki/pmwiki.php/Main/BrownNote", "/pmwiki/pmwiki.php/Main/CompleteMonster", "/pmwiki/pmwiki.php/Main/CompleteMonster", "/pmwiki/pmwiki.php/Main/CompleteMonster", "/pmwiki/pmwiki.php/Main/RealLife", "/pmwiki/pmwiki.php/Administrivia/NoRealLifeExamplesPlease", "/pmwiki/pmwiki.php/Main/AdorableAbomination", "/pmwiki/pmwiki.php/Main/AdaptationalAbomination", "/pmwiki/pmwiki.php/Main/Santabomination", "/pmwiki/pmwiki.php/Main/AngelicAbomination", "/pmwiki/pmwiki.php/Main/AnimalisticAbomination", "/pmwiki/pmwiki.php/Main/BotanicalAbomination", "/pmwiki/pmwiki.php/Main/DraconicAbomination", "/pmwiki/pmwiki.php/Main/HumanoidAbomination", "/pmwiki/pmwiki.php/Main/HumansAreCthulhu", "/pmwiki/pmwiki.php/Main/MechanicalAbomination", "/pmwiki/pmwiki.php/Main/UndeadAbomination", "/pmwiki/pmwiki.php/EldritchAbomination/AnimeAndManga", "/pmwiki/pmwiki.php/EldritchAbomination/ComicBooks", "/pmwiki/pmwiki.php/EldritchAbomination/FanFiction", "/pmwiki/pmwiki.php/EldritchAbomination/Film", "/pmwiki/pmwiki.php/EldritchAbomination/Literature", "/pmwiki/pmwiki.php/EldritchAbomination/LiveActionTV", "/pmwiki/pmwiki.php/EldritchAbomination/DoctorWho", "/pmwiki/pmwiki.php/EldritchAbomination/Music", "/pmwiki/pmwiki.php/EldritchAbomination/MythologyAndReligion", "/pmwiki/pmwiki.php/EldritchAbomination/TabletopGames", "/pmwiki/pmwiki.php/EldritchAbomination/DungeonsAndDragons", "/pmwiki/pmwiki.php/EldritchAbomination/VideoGames", "/pmwiki/pmwiki.php/EldritchAbomination/TheElderScrolls", "/pmwiki/pmwiki.php/EldritchAbomination/FinalFantasy", "/pmwiki/pmwiki.php/EldritchAbomination/Metroid", "/pmwiki/pmwiki.php/EldritchAbomination/MonsterHunter", "/pmwiki/pmwiki.php/EldritchAbomination/Pokemon", "/pmwiki/pmwiki.php/EldritchAbomination/RuneScape", "/pmwiki/pmwiki.php/EldritchAbomination/Webcomics", "/pmwiki/pmwiki.php/EldritchAbomination/WebOriginal", "/pmwiki/pmwiki.php/EldritchAbomination/SCPFoundation", "/pmwiki/pmwiki.php/EldritchAbomination/WesternAnimation", "/pmwiki/pmwiki.php/ComicStrip/ThisModernWorld", "https://www.dailykos.com/stories/2018/3/12/1748054/-Cartoon-The-thing-that-ate-America-s-brain", "/pmwiki/pmwiki.php/Main/BrainMonster", "/pmwiki/pmwiki.php/Main/EmotionEater", "/pmwiki/pmwiki.php/UsefulNotes/DonaldTrump", "/pmwiki/pmwiki.php/Main/BigBad", "/pmwiki/pmwiki.php/Main/FinalBossPreview", "/pmwiki/pmwiki.php/Main/CombatTentacles", "/pmwiki/pmwiki.php/Main/LivingShadow", "/pmwiki/pmwiki.php/Main/BigBad", "/pmwiki/pmwiki.php/Podcast/TheAdventureZoneBalance", "/pmwiki/pmwiki.php/Main/DungeonMaster", "/pmwiki/pmwiki.php/Main/Podcast", "/pmwiki/pmwiki.php/Podcast/CriticalHit", "/pmwiki/pmwiki.php/Main/NamesToRunAwayFromReallyFast", "/pmwiki/pmwiki.php/Podcast/WelcomeToNightVale", "/pmwiki/pmwiki.php/Main/CozyVoiceForCatastrophes", "/pmwiki/pmwiki.php/Main/CreepyGood", "/pmwiki/pmwiki.php/Podcast/TheHiddenAlmanac", "/pmwiki/pmwiki.php/Podcast/TheMagnusArchives", "/pmwiki/pmwiki.php/Main/HumanoidAbomination", "/pmwiki/pmwiki.php/Wrestling/WWE", "/pmwiki/pmwiki.php/Wrestling/BrayWyatt", "/pmwiki/pmwiki.php/Wrestling/TheNexus", "/pmwiki/pmwiki.php/Wrestling/LloydCthulowitz", "/pmwiki/pmwiki.php/Main/MadScientist", "/pmwiki/pmwiki.php/Main/PunnyName", "/pmwiki/pmwiki.php/Main/PartsUnknown", "/pmwiki/pmwiki.php/Main/ArsonMurderAndJaywalking", "/pmwiki/pmwiki.php/Roleplay/DestroyTheGodmodder", "/pmwiki/pmwiki.php/Main/DemonicDummy", "/pmwiki/pmwiki.php/Main/AuthorAvatar", "/pmwiki/pmwiki.php/Main/RealityBreakingParadox", "/pmwiki/pmwiki.php/Main/CosmicKeystone", "/pmwiki/pmwiki.php/Main/TheFourthWallWillNotProtectYou", "/pmwiki/pmwiki.php/Main/TimeAbyss", "/pmwiki/pmwiki.php/Main/BenevolentPrecursors", "/pmwiki/pmwiki.php/Main/FinalBoss", "/pmwiki/pmwiki.php/Main/ArsonMurderAndJaywalking", "/pmwiki/pmwiki.php/Main/InterfaceScrew", "/pmwiki/pmwiki.php/Main/DealWithTheDevil", "/pmwiki/pmwiki.php/Main/CameBackWrong", "/pmwiki/pmwiki.php/Main/BodyHorror", "/pmwiki/pmwiki.php/Main/WithGreatPowerComesGreatInsanity", "/pmwiki/pmwiki.php/Main/BattleAtTheCenterOfTheMind", "/pmwiki/pmwiki.php/Main/SentientCosmicForce", "/pmwiki/pmwiki.php/Main/UpToEleven", "/pmwiki/pmwiki.php/Main/ManBehindTheMan", "/pmwiki/pmwiki.php/Main/AIIsACrapshoot", "/pmwiki/pmwiki.php/Main/GiantSpaceFleaFromNowhere", "/pmwiki/pmwiki.php/Main/SentientCosmicForce", "/pmwiki/pmwiki.php/Main/BlueAndOrangeMorality", "/pmwiki/pmwiki.php/Main/SentientCosmicForce", "/pmwiki/pmwiki.php/Main/HumanoidAbomination", "/pmwiki/pmwiki.php/Roleplay/DinoAttackRPG", "/pmwiki/pmwiki.php/Roleplay/WeAreAllPokemonTrainers", "/pmwiki/pmwiki.php/Main/RealityWarping", "/pmwiki/pmwiki.php/Main/GoneHorriblyRight", "/pmwiki/pmwiki.php/Main/BrownNote", "/pmwiki/pmwiki.php/Roleplay/Apotheosis", "/pmwiki/pmwiki.php/Roleplay/InfiniteJustice", "/pmwiki/pmwiki.php/Main/PhysicalGod", "/pmwiki/pmwiki.php/Main/TheOmnipotent", "/pmwiki/pmwiki.php/Main/WordOfGod", "/pmwiki/pmwiki.php/Main/YouCannotGraspTheTrueForm", "/pmwiki/pmwiki.php/Main/YouCanNotGraspTheTrueForm", "/pmwiki/pmwiki.php/Main/MindRape", "/pmwiki/pmwiki.php/NightmareFuel/AltonTowers", "/pmwiki/pmwiki.php/Main/TomeOfEldritchLore", "/pmwiki/pmwiki.php/Main/ShoutOut", "/pmwiki/pmwiki.php/Main/AmbiguousRobots", "/pmwiki/pmwiki.php/Main/WetwareCPU", "/pmwiki/pmwiki.php/Main/BigBad", "/pmwiki/pmwiki.php/Main/RetCon", "/pmwiki/pmwiki.php/Main/MagnificentBastard", "/pmwiki/pmwiki.php/Main/TheChessmaster", "/pmwiki/pmwiki.php/Main/Satan", "/pmwiki/pmwiki.php/Main/WordOfGod", "/pmwiki/pmwiki.php/Main/ForWantOfANail", "/pmwiki/pmwiki.php/Main/DreamStealer", "/pmwiki/pmwiki.php/Main/SentientPhlebotinum", "/pmwiki/pmwiki.php/Main/NoBloodForPhlebotinum", "http://paizo.com/image/product/catalog/IMPTYV/IMPTYVHP004_360.jpeg", "/pmwiki/pmwiki.php/Main/OmnicidalManiac", "/pmwiki/pmwiki.php/Main/AsLongAsThereIsEvil", "/pmwiki/pmwiki.php/Main/PlanetEater", "/pmwiki/pmwiki.php/Main/ThisIsYourBrainOnEvil", "/pmwiki/pmwiki.php/Main/ThirteenIsUnlucky", "/pmwiki/pmwiki.php/Main/CainAndAbel", "http://funko.com/products/pop-literature-hp-lovecraft-cthulhu", "/pmwiki/pmwiki.php/Main/AdorableAbomination", "/pmwiki/pmwiki.php/Main/EldritchLocation", "/pmwiki/pmwiki.php/Main/MechanicalLifeforms", "/pmwiki/pmwiki.php/Main/HiveMind", "/pmwiki/pmwiki.php/Main/FisherKingdom", "/pmwiki/pmwiki.php/Main/SentientCosmicForce", "/pmwiki/pmwiki.php/Main/PhysicalGod", "/pmwiki/pmwiki.php/Main/AttackOfTheFiftyFootWhatever", "/pmwiki/pmwiki.php/Main/NighInvulnerability", "/pmwiki/pmwiki.php/Main/RealityWarper", "/pmwiki/pmwiki.php/Main/BlueAndOrangeMorality", "/pmwiki/pmwiki.php/Main/PunyEarthlings", "/pmwiki/pmwiki.php/Main/KillAllHumans", "/pmwiki/pmwiki.php/Main/GaiasVengeance", "/pmwiki/pmwiki.php/Main/TheDreaded", "/pmwiki/pmwiki.php/Main/YouKillItYouBoughtIt", "/pmwiki/pmwiki.php/Main/HumanoidAbomination", "/pmwiki/pmwiki.php/Main/TheHeartless", "/pmwiki/pmwiki.php/Main/FromNobodyToNightmare", "/pmwiki/pmwiki.php/Main/ColdBloodedTorture", "/pmwiki/pmwiki.php/Main/UpToEleven", "/pmwiki/pmwiki.php/Main/CosmicPlaything", "/pmwiki/pmwiki.php/Main/NiceJobBreakingItHero", "/pmwiki/pmwiki.php/Main/BeCarefulWhatYouWishFor", "/pmwiki/pmwiki.php/Main/TheHeartless", "/pmwiki/pmwiki.php/Main/TheHeartless", "/pmwiki/pmwiki.php/Main/TheCorruption", "/pmwiki/pmwiki.php/Main/UltimateEvil", "/pmwiki/pmwiki.php/Main/HiveMind", "/pmwiki/pmwiki.php/Main/PureMagicBeing", "/pmwiki/pmwiki.php/Main/LightEmUp", "/pmwiki/pmwiki.php/Main/AttackOfTheFiftyFootWhatever", "/pmwiki/pmwiki.php/Main/EyesDoNotBelongThere", "/pmwiki/pmwiki.php/Main/TheCorruption", "/pmwiki/pmwiki.php/Main/DemonicPossession", "/pmwiki/pmwiki.php/Main/HiveMind", "/pmwiki/pmwiki.php/Main/UltimateEvil", "/pmwiki/pmwiki.php/Main/TheCorruption", "/pmwiki/pmwiki.php/Main/GodzillaThreshold", "/pmwiki/pmwiki.php/Main/StarfishAlien", "/pmwiki/pmwiki.php/Main/SexSlave", "http://bogleech.com/animations.html", "http://scythemantis.deviantart.com/gallery/#/d1ovt1g", "http://www.bogleech.com/flash/FEARHOLE4.html", "https://www.youtube.com/watch?v=cl1UKqSoD9g", "https://www.youtube.com/watch?v=a6GEEi67atc", "/pmwiki/pmwiki.php/WebAnimation/BravestWarriors", "/pmwiki/pmwiki.php/Main/AnotherDimension", "http://m1.behance.net/rendition/modules/91159573/disp/48fd3f24abfd24873bd7e8af33af02e9.jpg", "/pmwiki/pmwiki.php/WebAnimation/ZeroPunctuation", "/pmwiki/pmwiki.php/Main/FunWithAcronyms", "https://youtu.be/zpMre7UTZQI", "/pmwiki/pmwiki.php/WebAnimation/Dreamscape", "/pmwiki/pmwiki.php/Main/CreepyCentipedes", "/pmwiki/pmwiki.php/Main/CreepyLongArms", "https://www.youtube.com/watch?v=fwR6mWJWuWQ"]}